canonicalwebteam/__init__.py
canonicalwebteam/discourse_docs/__init__.py
canonicalwebteam/discourse_docs/app.py
canonicalwebteam/discourse_docs/exceptions.py
canonicalwebteam/discourse_docs/models.py
canonicalwebteam/discourse_docs/parsers.py
tests/__init__.py
tests/test_app.py
tests/test_models.py
tests/fixtures/__init__.py
tests/fixtures/forum_mock.py
canonicalwebteam.discourse_docs-1.0.1.dist-info/LICENSE
canonicalwebteam.discourse_docs-1.0.1.dist-info/METADATA
canonicalwebteam.discourse_docs-1.0.1.dist-info/WHEEL
canonicalwebteam.discourse_docs-1.0.1.dist-info/top_level.txt
canonicalwebteam.discourse_docs-1.0.1.dist-info/RECORD
