Metadata-Version: 2.1
Name: canonicalwebteam.discourse-docs
Version: 1.0.1
Summary: Flask extension to integrate discourse content generated to docs to your website.
Home-page: https://github.com/canonical-webteam/canonicalwebteam.docs
Author: Canonical webteam
Author-email: webteam@canonical.com
License: UNKNOWN
Platform: UNKNOWN
Requires-Dist: Flask (>=1.0.2)
Requires-Dist: beautifulsoup4
Requires-Dist: humanize
Requires-Dist: python-dateutil
Requires-Dist: validators
